denis/__init__.py
denis/_native.py
denis/libdenis.darwin.arm64.dylib
denis/libdenis.darwin.x86_64.dylib
denis/libdenis.linux.x86_64.so
denis-0.0.11.dist-info/LICENSE
denis-0.0.11.dist-info/METADATA
denis-0.0.11.dist-info/WHEEL
denis-0.0.11.dist-info/top_level.txt
denis-0.0.11.dist-info/RECORD
