Metadata-Version: 2.1
Name: denis
Version: 0.0.11
Summary: A thin set of abstractions to perform geometrical operations on top of the latitude/longitude coordinate system
Home-page: https://github.com/mozaiques/denis
Author: Bastien Gandouet
Author-email: bastien@mozaiqu.es
License: MIT
Platform: UNKNOWN
Classifier: Development Status :: 3 - Alpha
Classifier: Intended Audience :: Developers
Classifier: License :: OSI Approved :: MIT License
Classifier: Programming Language :: Python :: 3.6
Requires-Dist: numpy
Requires-Dist: cffi (>=1.10)
